LICENSE
MANIFEST.in
README.md
setup.py
docs/HISTORY.txt
pipdeps/__init__.py
pipdeps/pipdeps.py
pipdeps.egg-info/PKG-INFO
pipdeps.egg-info/SOURCES.txt
pipdeps.egg-info/dependency_links.txt
pipdeps.egg-info/entry_points.txt
pipdeps.egg-info/namespace_packages.txt
pipdeps.egg-info/not-zip-safe
pipdeps.egg-info/requires.txt
pipdeps.egg-info/top_level.txt