Metadata-Version: 1.1
Name: pipdeps
Version: 0.0.3
Summary: Pipdeps shows/upgrades outdated packages with respect to existing                      dependencies.
Home-page: https://code.it4i.cz/sccs/pip-deps
Author: IT4Innovations
Author-email: support@it4i.cz
License: GPLv3+
Platform: UNKNOWN
Classifier: Operating System :: POSIX :: Linux
Classifier: Programming Language :: Python
Classifier: Programming Language :: Python :: 2.7
Classifier: Topic :: Software Development :: Libraries :: Python Modules
